voice_commander/__init__.py
voice_commander/__main__.py
voice_commander/_utils.py
voice_commander/actions.py
voice_commander/app.py
voice_commander/conditions.py
voice_commander/joy_listener.py
voice_commander/profile.py
voice_commander/py.typed
voice_commander/triggers.py
voice_commander/voice_listener.py
voice_commander/schema/__init__.py
voice_commander/schema/__main__.py
voice_commander/schema/schema.json
voice_commander/schema/v0.py
voice_commander-0.0.3.dist-info/LICENSE
voice_commander-0.0.3.dist-info/METADATA
voice_commander-0.0.3.dist-info/WHEEL
voice_commander-0.0.3.dist-info/top_level.txt
voice_commander-0.0.3.dist-info/RECORD
