Metadata-Version: 2.1
Name: voice-commander
Version: 0.0.3
Summary: Voice-controlled macros and hotkeys.
Home-page: https://github.com/spyoungtech/voice-commander
Author: Spencer Young
Author-email: spencer.young@spyoung.com
Project-URL: Documentation, https://voice-commander.readthedocs.io/en/latest/
Project-URL: Funding, https://github.com/sponsors/spyoungtech/
Project-URL: Source, https://github.com/spyoungtech/voice-commander
Project-URL: Tracker, https://github.com/spyoungtech/voice-commander/issues
Keywords: ahk,autohotkey,windows,mouse,keyboard,automation,pyautogui,voice-attack,voice,macro
Classifier: Intended Audience :: Developers
Classifier: Topic :: Desktop Environment
Classifier: Programming Language :: Python
Classifier: License :: OSI Approved :: MIT License
Classifier: Operating System :: Microsoft :: Windows
Classifier: Programming Language :: Python :: 3 :: Only
Classifier: Programming Language :: Python :: 3.12
Classifier: Typing :: Typed
Requires-Python: >=3.12.0
License-File: LICENSE
Requires-Dist: pydantic
Requires-Dist: SpeechRecognition
Requires-Dist: thefuzz
Requires-Dist: pyaudio
Requires-Dist: setuptools
Requires-Dist: ahk >=1.7.6
Requires-Dist: json-five
Requires-Dist: pyyaml
